README.txt
setup.cfg
setup.py
Chandler_FeedsPlugin.egg-info/PKG-INFO
Chandler_FeedsPlugin.egg-info/SOURCES.txt
Chandler_FeedsPlugin.egg-info/dependency_links.txt
Chandler_FeedsPlugin.egg-info/entry_points.txt
Chandler_FeedsPlugin.egg-info/top_level.txt
feeds/__init__.py
feeds/blocks.py
feeds/channels.py
feeds/feedparser.py
feeds/tests/TestFeedImport.py
feeds/tests/TestFeedIndexing.py
feeds/tests/__init__.py
feeds/tests/japanese.rdf
feeds/tests/osaf.blog.rss
