Metadata-Version: 1.0
Name: Chandler-FeedsPlugin
Version: 0.7-r15188
Summary: Simple RSS/Atom feed support for Chandler
Home-page: UNKNOWN
Author: OSAF
Author-email: UNKNOWN
License: UNKNOWN
Platform: UNKNOWN
Classifier: Development Status :: 3 - Alpha
Classifier: Environment :: Plugins
Classifier: Framework :: Chandler
Classifier: Intended Audience :: Developers
Classifier: License :: OSI Approved :: Apache Software License
Classifier: Operating System :: OS Independent
Classifier: Programming Language :: Python
Classifier: Topic :: Office/Business :: Groupware
